Workbook

Sheet P&L source
B2: P&L source
B4: USD in thousands | C4: 2016 Act | D4: 2017 Act | E4: 2018 Act
B5: Revenue from sales and services | C5: 177203 | D5: 188618 | E5: 208366
B6: Other revenue | C6: 3520 | D6: 2416 | E6: 2585
B7: Revenue | C7: =C5+C6 -> 180723 | D7: =D5+D6 -> 191034 | E7: =E5+E6 -> 210951
B9: Raw materials | C9: -139903.04 | D9: -138922.99 | E9: -150080.47
B10: Direct costs | C10: -2491.328 | D10: -11649.178 | E10: -7442.6496
B11: Cost for services | C11: -16389.594 | D11: -17878.31 | E11: -22293.312
B12: Lease costs | C12: -290.7264 | D12: -246.1312 | E12: -120.9216
B13: Other operating expenses | C13: -1330.9952 | D13: -1123.456 | E13: -1452.7744
B15: EBITDA | C15: =C7+SUM(C9:C13) -> 20317.317 | D15: =D7+SUM(D9:D13) -> 21213.936 | E15: =E7+SUM(E9:E13) -> 29560.874
B17: D&A | C17: -2907.8 | D17: -4649.8 | E17: -6430.66
B19: EBIT | C19: =C15+C17 -> 17409.517 | D19: =D15+D17 -> 16564.136 | E19: =E15+E17 -> 23130.214
B21: Financial income/expenses | C21: -1266.3 | D21: -2190.9 | E21: -2663.92
B22: Extraordinary income | C22: -317.58 | D22: -864.3 | E22: -320.26
B24: EBT | C24: =C19+C22+C21 -> 15825.637 | D24: =D19+D22+D21 -> 13508.936 | E24: =E19+E22+E21 -> 20146.034
B26: Taxes | C26: -3805.776 | D26: -3050.192 | E26: -3814.88
B28: Net Income | C28: =C24+C26 -> 12019.861 | D28: =D24+D26 -> 10458.744 | E28: =E24+E26 -> 16331.154

Sheet P&L Assumption
B2: P&L Assumption
B4: Case | C4: 1
C6: 16 | D6: =C6+1 -> 17 | E6: =D6+1 -> 18 | F6: =E6+1 -> 19 | G6: =F6+1 -> 20 | H6: =G6+1 -> 21 | I6: =H6+1 -> 22 | J6: =I6+1 -> 23
C7: Actual | D7: Actual | E7: Actual | F7: Forecast | G7: Forecast | H7: Forecast | I7: Forecast | J7: Forecast
B8: {='P&L source'!B5:E5} -> Revenue from sales and services | C8: 177203 | D8: 188618 | E8: 208366 | F8: =E8*(1+F9) -> 229202.6 | G8: =F8*(1+G9) -> 252122.86 | H8: =G8*(1+H9) -> 277335.15 | I8: =H8*(1+I9) -> 305068.66 | J8: =I8*(1+J9) -> 335575.53
B9: YoY Growth | D9: =D8/C8-1 -> 0.064417645 | E9: =E8/D8-1 -> 0.10469839 | F9: =CHOOSE($C$4,F10,F11,F12) -> 0.1 | G9: =CHOOSE($C$4,G10,G11,G12) -> 0.1 | H9: =CHOOSE($C$4,H10,H11,H12) -> 0.1 | I9: =CHOOSE($C$4,I10,I11,I12) -> 0.1 | J9: =CHOOSE($C$4,J10,J11,J12) -> 0.1
B10: Case 1 | F10: 0.1 | G10: 0.1 | H10: 0.1 | I10: 0.1 | J10: 0.1
B11: Case 2 | F11: 0.08 | G11: 0.08 | H11: 0.08 | I11: 0.08 | J11: 0.08
B12: Case 3 | F12: 0.06 | G12: 0.06 | H12: 0.06 | I12: 0.06 | J12: 0.06
B14: {='P&L source'!B6:E6} -> Other revenue | C14: 3520 | D14: 2416 | E14: 2585 | F14: =E14*(1+F15) -> 2585 | G14: =F14*(1+G15) -> 2585 | H14: =G14*(1+H15) -> 2585 | I14: =H14*(1+I15) -> 2585 | J14: =I14*(1+J15) -> 2585
B15: YoY Growth | D15: =D14/C14-1 -> -0.31363636 | E15: =E14/D14-1 -> 0.069950331 | F15: =CHOOSE($C$4,F16,F17,F18) -> 0 | G15: =CHOOSE($C$4,G16,G17,G18) -> 0 | H15: =CHOOSE($C$4,H16,H17,H18) -> 0 | I15: =CHOOSE($C$4,I16,I17,I18) -> 0 | J15: =CHOOSE($C$4,J16,J17,J18) -> 0
B16: Case 1 | F16: 0 | G16: 0 | H16: 0 | I16: 0 | J16: 0
B17: Case 2 | F17: 0 | G17: 0 | H17: 0 | I17: 0 | J17: 0
B18: Case 3 | F18: 0 | G18: 0 | H18: 0 | I18: 0 | J18: 0
B20: COGS | C20: =SUM('P&L source'!C9:C11) -> -158783.96 | D20: =SUM('P&L source'!D9:D11) -> -168450.48 | E20: =SUM('P&L source'!E9:E11) -> -179816.43 | F20: =F21*F$8 -> -194822.21 | G20: =G21*G$8 -> -214304.43 | H20: =H21*H$8 -> -235734.87 | I20: =I21*I$8 -> -259308.36 | J20: =J21*J$8 -> -285239.2
B21: As % of Sales | C21: =C20/C$8 -> -0.89605684 | D21: =D20/D$8 -> -0.89307742 | E21: =E20/E$8 -> -0.86298355 | F21: =CHOOSE($C$4,F22,F23,F24) -> -0.85 | G21: =CHOOSE($C$4,G22,G23,G24) -> -0.85 | H21: =CHOOSE($C$4,H22,H23,H24) -> -0.85 | I21: =CHOOSE($C$4,I22,I23,I24) -> -0.85 | J21: =CHOOSE($C$4,J22,J23,J24) -> -0.85
B22: Case 1 | F22: -0.85 | G22: -0.85 | H22: -0.85 | I22: -0.85 | J22: -0.85
B23: Case 2 | F23: -0.875 | G23: -0.875 | H23: -0.875 | I23: -0.875 | J23: -0.875
B24: Case 3 | F24: -0.9 | G24: -0.9 | H24: -0.9 | I24: -0.9 | J24: -0.9
B26: Other Expenses | C26: =SUM('P&L source'!C12:C13) -> -1621.7216 | D26: =SUM('P&L source'!D12:D13) -> -1369.5872 | E26: =SUM('P&L source'!E12:E13) -> -1573.696 | F26: =F27*F$8 -> -1719.0195 | G26: =G27*G$8 -> -1890.9215 | H26: =H27*H$8 -> -2080.0136 | I26: =I27*I$8 -> -2288.015 | J26: =J27*J$8 -> -2516.8164
B27: As % of Sales | C27: =C26/C$8 -> -0.0091517728 | D27: =D26/D$8 -> -0.0072611691 | E27: =E26/E$8 -> -0.0075525566 | F27: =CHOOSE($C$4,F28,F29,F30) -> -0.0075 | G27: =CHOOSE($C$4,G28,G29,G30) -> -0.0075 | H27: =CHOOSE($C$4,H28,H29,H30) -> -0.0075 | I27: =CHOOSE($C$4,I28,I29,I30) -> -0.0075 | J27: =CHOOSE($C$4,J28,J29,J30) -> -0.0075
B28: Case 1 | F28: -0.0075 | G28: -0.0075 | H28: -0.0075 | I28: -0.0075 | J28: -0.0075
B29: Case 2 | F29: -0.0085 | G29: -0.0085 | H29: -0.0085 | I29: -0.0085 | J29: -0.0085
B30: Case 3 | F30: -0.0095 | G30: -0.0095 | H30: -0.0095 | I30: -0.0095 | J30: -0.0095
B32: {='P&L source'!B17:E17} -> D&A | C32: -2907.8 | D32: -4649.8 | E32: -6430.66 | F32: =F33*F$8 -> -6876.078 | G32: =G33*G$8 -> -7563.6858 | H32: =H33*H$8 -> -8320.0544 | I32: =I33*I$8 -> -9152.0598 | J32: =J33*J$8 -> -10067.266
B33: As % of Sales | C33: =C32/C$8 -> -0.016409429 | D33: =D32/D$8 -> -0.024651942 | E33: =E32/E$8 -> -0.030862329 | F33: =CHOOSE($C$4,F34,F35,F36) -> -0.03 | G33: =CHOOSE($C$4,G34,G35,G36) -> -0.03 | H33: =CHOOSE($C$4,H34,H35,H36) -> -0.03 | I33: =CHOOSE($C$4,I34,I35,I36) -> -0.03 | J33: =CHOOSE($C$4,J34,J35,J36) -> -0.03
B34: Case 1 | F34: -0.03 | G34: -0.03 | H34: -0.03 | I34: -0.03 | J34: -0.03
B35: Case 2 | F35: -0.03 | G35: -0.03 | H35: -0.03 | I35: -0.03 | J35: -0.03
B36: Case 3 | F36: -0.03 | G36: -0.03 | H36: -0.03 | I36: -0.03 | J36: -0.03
B38: Interest Expense | C38: {='P&L source'!C21:E21} -> -1266.3 | D38: -2190.9 | E38: -2663.92 | F38: =F39*F$8 -> -2930.312 | G38: =G39*G$8 -> -3223.3432 | H38: =H39*H$8 -> -3545.6775 | I38: =I39*I$8 -> -3900.2453 | J38: =J39*J$8 -> -4290.2698
B39: As % of Sales | C39: =C38/C$8 -> -0.0071460415 | D39: =D38/D$8 -> -0.01161554 | E39: =E38/E$8 -> -0.012784811 | F39: =CHOOSE($C$4,F40,F41,F42) -> -0.012784811 | G39: =CHOOSE($C$4,G40,G41,G42) -> -0.012784811 | H39: =CHOOSE($C$4,H40,H41,H42) -> -0.012784811 | I39: =CHOOSE($C$4,I40,I41,I42) -> -0.012784811 | J39: =CHOOSE($C$4,J40,J41,J42) -> -0.012784811
B40: Case 1 | F40: =E39 -> -0.012784811 | G40: =F39 -> -0.012784811 | H40: =G39 -> -0.012784811 | I40: =H39 -> -0.012784811 | J40: =I39 -> -0.012784811
B41: Case 2 | F41: =F40 -> -0.012784811 | G41: =G40 -> -0.012784811 | H41: =H40 -> -0.012784811 | I41: =I40 -> -0.012784811 | J41: =J40 -> -0.012784811
B42: Case 3 | F42: =F41 -> -0.012784811 | G42: =G41 -> -0.012784811 | H42: =H41 -> -0.012784811 | I42: =I41 -> -0.012784811 | J42: =J41 -> -0.012784811
B44: ='P&L source'!B22 -> Extraordinary income | C44: ='P&L source'!C22 -> -317.58 | D44: ='P&L source'!D22 -> -864.3 | E44: ='P&L source'!E22 -> -320.26 | F44: =F45*F$8 -> 0 | G44: =G45*G$8 -> 0 | H44: =H45*H$8 -> 0 | I44: =I45*I$8 -> 0 | J44: =J45*J$8 -> 0
B45: As % of Sales | C45: =C44/C$8 -> -0.0017921818 | D45: =D44/D$8 -> -0.0045822774 | E45: =E44/E$8 -> -0.001537007 | F45: =CHOOSE($C$4,F46,F47,F48) -> 0 | G45: =CHOOSE($C$4,G46,G47,G48) -> 0 | H45: =CHOOSE($C$4,H46,H47,H48) -> 0 | I45: =CHOOSE($C$4,I46,I47,I48) -> 0 | J45: =CHOOSE($C$4,J46,J47,J48) -> 0
B46: Case 1 | F46: 0 | G46: 0 | H46: 0 | I46: 0 | J46: 0
B47: Case 2 | F47: 0 | G47: 0 | H47: 0 | I47: 0 | J47: 0
B48: Case 3 | F48: 0 | G48: 0 | H48: 0 | I48: 0 | J48: 0

Sheet P&L
D2: Statement of Profit or Loss
E4: 16 | F4: =E4+1 -> 17 | G4: =F4+1 -> 18 | H4: =G4+1 -> 19 | I4: =H4+1 -> 20 | J4: =I4+1 -> 21 | K4: =J4+1 -> 22 | L4: =K4+1 -> 23
E5: Actual | F5: Actual | G5: Actual | H5: Forecast | I5: Forecast | J5: Forecast | K5: Forecast | L5: Forecast
D6: {='P&L Assumption'!B8:J8} -> Revenue from sales and services | E6: 177203 | F6: 188618 | G6: 208366 | H6: 229202.6 | I6: 252122.86 | J6: 277335.15 | K6: 305068.66 | L6: 335575.53
D7: {='P&L Assumption'!B14:J14} -> Other revenue | E7: 3520 | F7: 2416 | G7: 2585 | H7: 2585 | I7: 2585 | J7: 2585 | K7: 2585 | L7: 2585
D8: Total Revenue | E8: =SUM(E6:E7) -> 180723 | F8: =SUM(F6:F7) -> 191034 | G8: =SUM(G6:G7) -> 210951 | H8: =SUM(H6:H7) -> 231787.6 | I8: =SUM(I6:I7) -> 254707.86 | J8: =SUM(J6:J7) -> 279920.15 | K8: =SUM(K6:K7) -> 307653.66 | L8: =SUM(L6:L7) -> 338160.53
D9: {='P&L Assumption'!B20:J20} -> COGS | E9: -158783.96 | F9: -168450.48 | G9: -179816.43 | H9: -194822.21 | I9: -214304.43 | J9: -235734.87 | K9: -259308.36 | L9: -285239.2
D10: Gross Profit | E10: =SUM(E8:E9) -> 21939.039 | F10: =SUM(F8:F9) -> 22583.523 | G10: =SUM(G8:G9) -> 31134.57 | H10: =SUM(H8:H9) -> 36965.39 | I10: =SUM(I8:I9) -> 40403.429 | J10: =SUM(J8:J9) -> 44185.272 | K10: =SUM(K8:K9) -> 48345.299 | L10: =SUM(L8:L9) -> 52921.329
D11: {='P&L Assumption'!B26:J26} -> Other Expenses | E11: -1621.7216 | F11: -1369.5872 | G11: -1573.696 | H11: -1719.0195 | I11: -1890.9215 | J11: -2080.0136 | K11: -2288.015 | L11: -2516.8164
D12: EBITDA | E12: =SUM(E10:E11) -> 20317.317 | F12: =SUM(F10:F11) -> 21213.936 | G12: =SUM(G10:G11) -> 29560.874 | H12: =SUM(H10:H11) -> 35246.371 | I12: =SUM(I10:I11) -> 38512.508 | J12: =SUM(J10:J11) -> 42105.258 | K12: =SUM(K10:K11) -> 46057.284 | L12: =SUM(L10:L11) -> 50404.513
D13: {='P&L Assumption'!B32:J32} -> D&A | E13: -2907.8 | F13: -4649.8 | G13: -6430.66 | H13: -6876.078 | I13: -7563.6858 | J13: -8320.0544 | K13: -9152.0598 | L13: -10067.266
D14: EBIT | E14: =SUM(E12:E13) -> 17409.517 | F14: =SUM(F12:F13) -> 16564.136 | G14: =SUM(G12:G13) -> 23130.214 | H14: =SUM(H12:H13) -> 28370.293 | I14: =SUM(I12:I13) -> 30948.822 | J14: =SUM(J12:J13) -> 33785.204 | K14: =SUM(K12:K13) -> 36905.224 | L14: =SUM(L12:L13) -> 40337.247
D15: {='P&L Assumption'!B38:J38} -> Interest Expense | E15: -1266.3 | F15: -2190.9 | G15: -2663.92 | H15: -2930.312 | I15: -3223.3432 | J15: -3545.6775 | K15: -3900.2453 | L15: -4290.2698
D16: {='P&L Assumption'!B44:J44} -> Extraordinary income | E16: -317.58 | F16: -864.3 | G16: -320.26 | H16: 0 | I16: 0 | J16: 0 | K16: 0 | L16: 0
D17: EBT | E17: =SUM(E14:E16) -> 15825.637 | F17: =SUM(F14:F16) -> 13508.936 | G17: =SUM(G14:G16) -> 20146.034 | H17: =SUM(H14:H16) -> 25439.981 | I17: =SUM(I14:I16) -> 27725.479 | J17: =SUM(J14:J16) -> 30239.526 | K17: =SUM(K14:K16) -> 33004.979 | L17: =SUM(L14:L16) -> 36046.977
D18: Tax | E18: {='P&L source'!C26:E26} -> -3805.776 | F18: -3050.192 | G18: -3814.88 | H18: =H17*H19 -> -5559.7697 | I18: =I17*I19 -> -6059.2529 | J18: =J17*J19 -> -6608.6844 | K18: =K17*K19 -> -7213.0591 | L18: =L17*L19 -> -7877.8713
D19: As % of EBT | E19: =E18/E17 -> -0.24048169 | F19: =F18/F17 -> -0.22579069 | G19: =G18/G17 -> -0.18936134 | H19: =AVERAGE(E19:G19) -> -0.21854458 | I19: =H19 -> -0.21854458 | J19: =I19 -> -0.21854458 | K19: =J19 -> -0.21854458 | L19: =K19 -> -0.21854458
D20: Net Income | E20: =SUM(E17:E18) -> 12019.861 | F20: =SUM(F17:F18) -> 10458.744 | G20: =SUM(G17:G18) -> 16331.154 | H20: =SUM(H17:H18) -> 19880.211 | I20: =SUM(I17:I18) -> 21666.226 | J20: =SUM(J17:J18) -> 23630.842 | K20: =SUM(K17:K18) -> 25791.92 | L20: =SUM(L17:L18) -> 28169.106

Sheet BS source
B2: BS source
B4: USD in thousands | D4: 31Dec16 Act | E4: 31Dec17 Act | F4: 31Dec18 Act | H4: USD in thousands | J4: 31Dec16 Act | K4: 31Dec17 Act | L4: 31Dec18 Act
B5: Intangible assets | D5: 5961.6 | E5: 5840 | F5: 5650 | H5: Share Capital | J5: 6784.8 | K5: 6800 | L5: 7508
B6: PP&E | D6: 45106.4 | E6: 49072.4 | F6: 56109.2 | H6: Reserves | J6: 46224 | K6: 44414.4 | L6: 46513.2
B7: Financial assets | D7: 8824 | E7: 9831 | F7: 10323 | H7: Retained earnings | J7: 16393.7 | K7: 25993.7 | L7: 21516
H8: Profit/(loss) for the year | J8: 12019.861 | K8: 10458.744 | L8: 16331.154
B9: Fixed assets | D9: =D7+D6+D5 -> 59892 | E9: =E7+E6+E5 -> 64743.4 | F9: =F7+F6+F5 -> 72082.2 | H9: Total Equity | J9: =SUM(J5:J8) -> 81422.361 | K9: =SUM(K5:K8) -> 87666.844 | L9: =SUM(L5:L8) -> 91868.354
B11: Inventory | D11: 31167.2 | E11: 36396.8 | F11: 46212 | H11: Trade payable | J11: 15891.2 | K11: 26351.6 | L11: 36189.6
B12: Trade receivables | D12: 32883.6 | E12: 38556 | F12: 43581.6 | H12: Other liabilities | J12: 5315 | K12: 4334 | L12: 6473.0464
B13: Other assets | D13: 8841.6 | E13: 11359.2 | F13: 17602.8 | H13: Deferred taxes | J13: 478.83867 | K13: 1217.956 | L13: 1760.4
H14: Provisions for retirement benefits | J14: 175.2 | K14: 248.4 | L14: 240
B15: Cash and equivalents | D15: 11791.2 | E15: 19408.8 | F15: 8173.6
B16: Non fixed assets | D16: =+D15+D13+D12+D11 -> 84683.6 | E16: =+E15+E13+E12+E11 -> 105720.8 | F16: =+F15+F13+F12+F11 -> 115570 | H16: Bank borrowings | J16: 37402.6 | K16: 45594.6 | L16: 50680.4
H17: Other Financial liabilities | J17: 3890.4 | K17: 5050.8 | L17: 440.4
H18: Total Liabilities | J18: =J17+J16+SUM(J11:J14) -> 63153.239 | K18: =K17+K16+SUM(K11:K14) -> 82797.356 | L18: =L17+L16+SUM(L11:L14) -> 95783.846
B20: Total Assets | D20: =D16+D9 -> 144575.6 | E20: =E16+E9 -> 170464.2 | F20: =F16+F9 -> 187652.2 | H20: Total Liabilities & Equity | J20: =J18+J9 -> 144575.6 | K20: =K18+K9 -> 170464.2 | L20: =L18+L9 -> 187652.2
J23: =J20-D20 -> 0 | K23: =K20-E20 -> 0 | L23: =L20-F20 -> 0

Sheet BS Assumption
B2: BS Assumption
C4: 16 | D4: =C4+1 -> 17 | E4: =D4+1 -> 18 | F4: =E4+1 -> 19 | G4: =F4+1 -> 20 | H4: =G4+1 -> 21 | I4: =H4+1 -> 22 | J4: =I4+1 -> 23
C5: Actual | D5: Actual | E5: Actual | F5: Forecast | G5: Forecast | H5: Forecast | I5: Forecast | J5: Forecast
B6: ='BS source'!B12 -> Trade receivables | C6: {='BS source'!D12:F12} -> 32883.6 | D6: 38556 | E6: 43581.6 | F6: =F7*'P&L'!H6/365 -> 45774.988 | G6: =G7*'P&L'!I6/365 -> 50352.487 | H6: =H7*'P&L'!J6/365 -> 55387.735 | I6: =I7*'P&L'!K6/365 -> 60926.509 | J6: =J7*'P&L'!L6/365 -> 67019.16
B7: DSO | C7: =C6/'P&L'!E6*365 -> 67.733131 | D7: =D6/'P&L'!F6*365 -> 74.610801 | E7: =E6/'P&L'!G6*365 -> 76.342993 | F7: =AVERAGE(C7:E7) -> 72.895641 | G7: =F7 -> 72.895641 | H7: =G7 -> 72.895641 | I7: =H7 -> 72.895641 | J7: =I7 -> 72.895641
B9: ='BS source'!B11 -> Inventory | C9: {='BS source'!D11:F11} -> 31167.2 | D9: 36396.8 | E9: 46212 | F9: =F10*'P&L'!H9/365 -> 43468.115 | G9: =G10*'P&L'!I9/365 -> 47814.926 | H9: =H10*'P&L'!J9/365 -> 52596.419 | I9: =I10*'P&L'!K9/365 -> 57856.061 | J9: =J10*'P&L'!L9/365 -> 63641.667
B10: DIO | C10: =C9/'P&L'!E9*365 -> -71.644692 | D10: =D9/'P&L'!F9*365 -> -78.864912 | E10: =E9/'P&L'!G9*365 -> -93.80333 | F10: =AVERAGE(C10:E10) -> -81.437645 | G10: =F10 -> -81.437645 | H10: =G10 -> -81.437645 | I10: =H10 -> -81.437645 | J10: =I10 -> -81.437645
B12: ='BS source'!H11 -> Trade payable | C12: {='BS source'!J11:L11} -> 15891.2 | D12: 26351.6 | E12: 36189.6 | F12: =F13*'P&L'!H9/365 -> 29728.214 | G12: =G13*'P&L'!I9/365 -> 32701.036 | H12: =H13*'P&L'!J9/365 -> 35971.139 | I12: =I13*'P&L'!K9/365 -> 39568.253 | J12: =J13*'P&L'!L9/365 -> 43525.078
B13: DPO | C13: =C12/'P&L'!E9*365 -> -36.529433 | D13: =D12/'P&L'!F9*365 -> -57.098883 | E13: =E12/'P&L'!G9*365 -> -73.459383 | F13: =AVERAGE(C13:E13) -> -55.695899 | G13: =F13 -> -55.695899 | H13: =G13 -> -55.695899 | I13: =H13 -> -55.695899 | J13: =I13 -> -55.695899
B15: ='BS source'!B6 -> PP&E | C15: {='BS source'!D6:F6} -> 45106.4 | D15: 49072.4 | E15: 56109.2 | F15: =F16*'P&L'!H6 -> 59898.019 | G15: =G16*'P&L'!I6 -> 65887.821 | H15: =H16*'P&L'!J6 -> 72476.603 | I15: =I16*'P&L'!K6 -> 79724.263 | J15: =J16*'P&L'!L6 -> 87696.689
B16: As % of Sales | C16: =C15/'P&L'!E6 -> 0.25454648 | D16: =D15/'P&L'!F6 -> 0.26016817 | E16: =E15/'P&L'!G6 -> 0.26928194 | F16: =AVERAGE(C16:E16) -> 0.2613322 | G16: =F16 -> 0.2613322 | H16: =G16 -> 0.2613322 | I16: =H16 -> 0.2613322 | J16: =I16 -> 0.2613322
B18: ='BS source'!B13 -> Other assets | C18: {='BS source'!D13:F13} -> 8841.6 | D18: 11359.2 | E18: 17602.8 | F18: =F19*'P&L'!H6 -> 14867.518 | G18: =G19*'P&L'!I6 -> 16354.27 | H18: =H19*'P&L'!J6 -> 17989.697 | I18: =I19*'P&L'!K6 -> 19788.667 | J18: =J19*'P&L'!L6 -> 21767.534
B19: =B16 -> As % of Sales | C19: =C18/'P&L'!E6 -> 0.049895318 | D19: =D18/'P&L'!F6 -> 0.060223308 | E19: =E18/'P&L'!G6 -> 0.084480194 | F19: =AVERAGE(C19:E19) -> 0.064866273 | G19: =F19 -> 0.064866273 | H19: =G19 -> 0.064866273 | I19: =H19 -> 0.064866273 | J19: =I19 -> 0.064866273
B21: ='BS source'!H12 -> Other liabilities | C21: =SUM('BS source'!J12:J14) -> 5969.0387 | D21: =SUM('BS source'!K12:K14) -> 5800.356 | E21: =SUM('BS source'!L12:L14) -> 8473.4464 | F21: =F22*'P&L'!H6 -> 8029.9438 | G21: =G22*'P&L'!I6 -> 8832.9382 | H21: =H22*'P&L'!J6 -> 9716.2321 | I21: =I22*'P&L'!K6 -> 10687.855 | J21: =J22*'P&L'!L6 -> 11756.641
B22: =B19 -> As % of Sales | C22: =C21/'P&L'!E6 -> 0.03368475 | D22: =D21/'P&L'!F6 -> 0.030751869 | E22: =E21/'P&L'!G6 -> 0.040666166 | F22: =AVERAGE(C22:E22) -> 0.035034262 | G22: =F22 -> 0.035034262 | H22: =G22 -> 0.035034262 | I22: =H22 -> 0.035034262 | J22: =I22 -> 0.035034262

Sheet BS
B2: Balance Sheet
C4: 16 | D4: =C4+1 -> 17 | E4: =D4+1 -> 18 | F4: =E4+1 -> 19 | G4: =F4+1 -> 20 | H4: =G4+1 -> 21 | I4: =H4+1 -> 22 | J4: =I4+1 -> 23
C5: Actual | D5: Actual | E5: Actual | F5: Forecast | G5: Forecast | H5: Forecast | I5: Forecast | J5: Forecast
B6: ='BS source'!B5 -> Intangible assets | C6: {='BS source'!D5:F5} -> 5961.6 | D6: 5840 | E6: 5650 | F6: =E6 -> 5650 | G6: =F6 -> 5650 | H6: =G6 -> 5650 | I6: =H6 -> 5650 | J6: =I6 -> 5650
B7: {='BS Assumption'!B15:J15} -> PP&E | C7: 45106.4 | D7: 49072.4 | E7: 56109.2 | F7: 59898.019 | G7: 65887.821 | H7: 72476.603 | I7: 79724.263 | J7: 87696.689
B8: ='BS source'!B7 -> Financial assets | C8: {='BS source'!D7:F7} -> 8824 | D8: 9831 | E8: 10323 | F8: =E8 -> 10323 | G8: =F8 -> 10323 | H8: =G8 -> 10323 | I8: =H8 -> 10323 | J8: =I8 -> 10323
B9: {='BS Assumption'!B9:J9} -> Inventory | C9: 31167.2 | D9: 36396.8 | E9: 46212 | F9: 43468.115 | G9: 47814.926 | H9: 52596.419 | I9: 57856.061 | J9: 63641.667
B10: {='BS Assumption'!B6:J6} -> Trade receivables | C10: 32883.6 | D10: 38556 | E10: 43581.6 | F10: 45774.988 | G10: 50352.487 | H10: 55387.735 | I10: 60926.509 | J10: 67019.16
B11: {='BS Assumption'!B18:J18} -> Other assets | C11: 8841.6 | D11: 11359.2 | E11: 17602.8 | F11: 14867.518 | G11: 16354.27 | H11: 17989.697 | I11: 19788.667 | J11: 21767.534
B12: ='BS source'!B15 -> Cash and equivalents | C12: {='BS source'!D15:F15} -> 11791.2 | D12: 19408.8 | E12: 8173.6 | F12: {=CF!F36:J36} -> 20645.883 | G12: 29687.06 | H12: 39430.349 | I12: 49945.961 | J12: 61311.127
B13: Total Assets | C13: =SUM(C6:C12) -> 144575.6 | D13: =SUM(D6:D12) -> 170464.2 | E13: =SUM(E6:E12) -> 187652.2 | F13: =SUM(F6:F12) -> 200627.52 | G13: =SUM(G6:G12) -> 226069.56 | H13: =SUM(H6:H12) -> 253853.8 | I13: =SUM(I6:I12) -> 284214.46 | J13: =SUM(J6:J12) -> 317409.18
B15: {='BS Assumption'!B12:J12} -> Trade payable | C15: 15891.2 | D15: 26351.6 | E15: 36189.6 | F15: 29728.214 | G15: 32701.036 | H15: 35971.139 | I15: 39568.253 | J15: 43525.078
B16: {='BS Assumption'!B21:J21} -> Other liabilities | C16: 5969.0387 | D16: 5800.356 | E16: 8473.4464 | F16: 8029.9438 | G16: 8832.9382 | H16: 9716.2321 | I16: 10687.855 | J16: 11756.641
B17: Financial Liabilities | C17: =SUM('BS source'!J16:J17) -> 41293 | D17: =SUM('BS source'!K16:K17) -> 50645.4 | E17: =SUM('BS source'!L16:L17) -> 51120.8 | F17: =E17 -> 51120.8 | G17: =F17 -> 51120.8 | H17: =G17 -> 51120.8 | I17: =H17 -> 51120.8 | J17: =I17 -> 51120.8
B18: Total Equity | C18: {='BS source'!J9:L9} -> 81422.361 | D18: 87666.844 | E18: 91868.354 | F18: =E18+'P&L'!H20 -> 111748.56 | G18: =F18+'P&L'!I20 -> 133414.79 | H18: =G18+'P&L'!J20 -> 157045.63 | I18: =H18+'P&L'!K20 -> 182837.55 | J18: =I18+'P&L'!L20 -> 211006.66
B19: Total Liabilities & Equity | C19: =SUM(C15:C18) -> 144575.6 | D19: =SUM(D15:D18) -> 170464.2 | E19: =SUM(E15:E18) -> 187652.2 | F19: =SUM(F15:F18) -> 200627.52 | G19: =SUM(G15:G18) -> 226069.56 | H19: =SUM(H15:H18) -> 253853.8 | I19: =SUM(I15:I18) -> 284214.46 | J19: =SUM(J15:J18) -> 317409.18
B21: Check | C21: =C13-C19 -> 0 | D21: =D13-D19 -> 0 | E21: =E13-E19 -> 0 | F21: =F13-F19 -> 0 | G21: =G13-G19 -> 0 | H21: =H13-H19 -> 0 | I21: =I13-I19 -> 0 | J21: =J13-J19 -> 0

Sheet CF
B2: Cash Flow Statement
C4: 16 | D4: =C4+1 -> 17 | E4: =D4+1 -> 18 | F4: =E4+1 -> 19 | G4: =F4+1 -> 20 | H4: =G4+1 -> 21 | I4: =H4+1 -> 22 | J4: =I4+1 -> 23
C5: Actual | D5: Actual | E5: Actual | F5: Forecast | G5: Forecast | H5: Forecast | I5: Forecast | J5: Forecast
B6: {='P&L'!D14:L14} -> EBIT | C6: 17409.517 | D6: 16564.136 | E6: 23130.214 | F6: 28370.293 | G6: 30948.822 | H6: 33785.204 | I6: 36905.224 | J6: 40337.247
B7: {='P&L'!D19:L19} -> As % of EBT | C7: -0.24048169 | D7: -0.22579069 | E7: -0.18936134 | F7: -0.21854458 | G7: -0.21854458 | H7: -0.21854458 | I7: -0.21854458 | J7: -0.21854458
B8: Tax | C8: =C7*C6 -> -4186.6701 | D8: =D7*D6 -> -3740.0277 | E8: =E7*E6 -> -4379.9683 | F8: =F7*F6 -> -6200.1735 | G8: =G7*G6 -> -6763.6971 | H8: =H7*H6 -> -7383.573 | I8: =I7*I6 -> -8065.4366 | J8: =J7*J6 -> -8815.4864
B9: NOPAT | C9: =SUM(C6,C8) -> 13222.847 | D9: =SUM(D6,D8) -> 12824.108 | E9: =SUM(E6,E8) -> 18750.245 | F9: =SUM(F6,F8) -> 22170.119 | G9: =SUM(G6,G8) -> 24185.125 | H9: =SUM(H6,H8) -> 26401.631 | I9: =SUM(I6,I8) -> 28839.788 | J9: =SUM(J6,J8) -> 31521.76
B11: Add Back Depreciation | C11: {=-'P&L'!E13:L13} -> 2907.8 | D11: 4649.8 | E11: 6430.66 | F11: 6876.078 | G11: 7563.6858 | H11: 8320.0544 | I11: 9152.0598 | J11: 10067.266
B12: Gross Cash Flows | C12: =SUM(C9,C11) -> 16130.647 | D12: =SUM(D9,D11) -> 17473.908 | E12: =SUM(E9,E11) -> 25180.905 | F12: =SUM(F9,F11) -> 29046.197 | G12: =SUM(G9,G11) -> 31748.81 | H12: =SUM(H9,H11) -> 34721.685 | I12: =SUM(I9,I11) -> 37991.848 | J12: =SUM(J9,J11) -> 41589.026
B14: {=BS!B9:B10} -> Inventory | D14: =-(BS!D9-BS!C9) -> -5229.6 | E14: =-(BS!E9-BS!D9) -> -9815.2 | F14: =-(BS!F9-BS!E9) -> 2743.8852 | G14: =-(BS!G9-BS!F9) -> -4346.8115 | H14: =-(BS!H9-BS!G9) -> -4781.4926 | I14: =-(BS!I9-BS!H9) -> -5259.6419 | J14: =-(BS!J9-BS!I9) -> -5785.6061
B15: Trade receivables | D15: =-(BS!D10-BS!C10) -> -5672.4 | E15: =-(BS!E10-BS!D10) -> -5025.6 | F15: =-(BS!F10-BS!E10) -> -2193.3878 | G15: =-(BS!G10-BS!F10) -> -4577.4988 | H15: =-(BS!H10-BS!G10) -> -5035.2487 | I15: =-(BS!I10-BS!H10) -> -5538.7735 | J15: =-(BS!J10-BS!I10) -> -6092.6509
B16: =BS!B15 -> Trade payable | D16: =BS!D15-BS!C15 -> 10460.4 | E16: =BS!E15-BS!D15 -> 9838 | F16: =BS!F15-BS!E15 -> -6461.3858 | G16: =BS!G15-BS!F15 -> 2972.8214 | H16: =BS!H15-BS!G15 -> 3270.1036 | I16: =BS!I15-BS!H15 -> 3597.1139 | J16: =BS!J15-BS!I15 -> 3956.8253
B17: Investments in Working Capital | D17: =SUM(D14:D16) -> -441.6 | E17: =SUM(E14:E16) -> -5002.8 | F17: =SUM(F14:F16) -> -5910.8884 | G17: =SUM(G14:G16) -> -5951.4888 | H17: =SUM(H14:H16) -> -6546.6377 | I17: =SUM(I14:I16) -> -7201.3015 | J17: =SUM(J14:J16) -> -7921.4316
B19: =BS!B11 -> Other assets | D19: =-(BS!D11-BS!C11) -> -2517.6 | E19: =-(BS!E11-BS!D11) -> -6243.6 | F19: =-(BS!F11-BS!E11) -> 2735.2815 | G19: =-(BS!G11-BS!F11) -> -1486.7518 | H19: =-(BS!H11-BS!G11) -> -1635.427 | I19: =-(BS!I11-BS!H11) -> -1798.9697 | J19: =-(BS!J11-BS!I11) -> -1978.8667
B20: =BS!B16 -> Other liabilities | D20: =BS!D16-BS!C16 -> -168.68267 | E20: =BS!E16-BS!D16 -> 2673.0904 | F20: =BS!F16-BS!E16 -> -443.50258 | G20: =BS!G16-BS!F16 -> 802.99438 | H20: =BS!H16-BS!G16 -> 883.29382 | I20: =BS!I16-BS!H16 -> 971.62321 | J20: =BS!J16-BS!I16 -> 1068.7855
B21: Investments in Other Assets | D21: =SUM(D19:D20) -> -2686.2827 | E21: =SUM(E19:E20) -> -3570.5096 | F21: =SUM(F19:F20) -> 2291.7789 | G21: =SUM(G19:G20) -> -683.75746 | H21: =SUM(H19:H20) -> -752.13321 | I21: =SUM(I19:I20) -> -827.34653 | J21: =SUM(J19:J20) -> -910.08118
B23: CapEx | D23: =-(BS!D7-BS!C7)+'P&L'!F13 -> -8615.8 | E23: =-(BS!E7-BS!D7)+'P&L'!G13 -> -13467.46 | F23: =-(BS!F7-BS!E7)+'P&L'!H13 -> -10664.897 | G23: =-(BS!G7-BS!F7)+'P&L'!I13 -> -13553.488 | H23: =-(BS!H7-BS!G7)+'P&L'!J13 -> -14908.836 | I23: =-(BS!I7-BS!H7)+'P&L'!K13 -> -16399.72 | J23: =-(BS!J7-BS!I7)+'P&L'!L13 -> -18039.692
B25: Other Investments | D25: =-(BS!D6-BS!C6)-(BS!D8-BS!C8) -> -885.4 | E25: =-(BS!E6-BS!D6)-(BS!E8-BS!D8) -> -302 | F25: =-(BS!F6-BS!E6)-(BS!F8-BS!E8) -> 0 | G25: =-(BS!G6-BS!F6)-(BS!G8-BS!F8) -> 0 | H25: =-(BS!H6-BS!G6)-(BS!H8-BS!G8) -> 0 | I25: =-(BS!I6-BS!H6)-(BS!I8-BS!H8) -> 0 | J25: =-(BS!J6-BS!I6)-(BS!J8-BS!I8) -> 0
B27: {=_xlfn.ANCHORARRAY('P&L'!D16)} -> Extraordinary income | C27: -317.58 | D27: -864.3 | E27: -320.26 | F27: 0 | G27: 0 | H27: 0 | I27: 0 | J27: 0
B29: UFCF | D29: =SUM(D12,D17,D21,D23,D25,D27) -> 3980.5256 | E29: =SUM(E12,E17,E21,E23,E25,E27) -> 2517.8757 | F29: =SUM(F12,F17,F21,F23,F25,F27) -> 14762.191 | G29: =SUM(G12,G17,G21,G23,G25,G27) -> 11560.076 | H29: =SUM(H12,H17,H21,H23,H25,H27) -> 12514.078 | I29: =SUM(I12,I17,I21,I23,I25,I27) -> 13563.479 | J29: =SUM(J12,J17,J21,J23,J25,J27) -> 14717.821
B31: {=_xlfn.ANCHORARRAY('P&L'!D15)} -> Interest Expense | C31: -1266.3 | D31: -2190.9 | E31: -2663.92 | F31: -2930.312 | G31: -3223.3432 | H31: -3545.6775 | I31: -3900.2453 | J31: -4290.2698
B32: Tax Reversed | C32: ='P&L'!E18-CF!C8 -> 380.89414 | D32: ='P&L'!F18-CF!D8 -> 689.83572 | E32: ='P&L'!G18-CF!E8 -> 565.08834 | F32: ='P&L'!H18-CF!F8 -> 640.40379 | G32: ='P&L'!I18-CF!G8 -> 704.44417 | H32: ='P&L'!J18-CF!H8 -> 774.88859 | I32: ='P&L'!K18-CF!I8 -> 852.37745 | J32: ='P&L'!L18-CF!J8 -> 937.61519
B33: {=BS!B17:B18} -> Financial Liabilities | D33: =BS!D17-BS!C17 -> 9352.4 | E33: =BS!E17-BS!D17 -> 475.4 | F33: =BS!F17-BS!E17 -> 0 | G33: =BS!G17-BS!F17 -> 0 | H33: =BS!H17-BS!G17 -> 0 | I33: =BS!I17-BS!H17 -> 0 | J33: =BS!J17-BS!I17 -> 0
B34: Total Equity | D34: =(BS!D18-BS!C18)-'P&L'!F20 -> -4214.2613 | E34: =(BS!E18-BS!D18)-'P&L'!G20 -> -12129.644 | F34: =(BS!F18-BS!E18)-'P&L'!H20 -> 0 | G34: =(BS!G18-BS!F18)-'P&L'!I20 -> 0 | H34: =(BS!H18-BS!G18)-'P&L'!J20 -> 0 | I34: =(BS!I18-BS!H18)-'P&L'!K20 -> 0 | J34: =(BS!J18-BS!I18)-'P&L'!L20 -> 0
B35: Net Cash Flows | D35: =SUM(D31:D34,D29) -> 7617.6 | E35: =SUM(E31:E34,E29) -> -11235.2 | F35: =SUM(F31:F34,F29) -> 12472.283 | G35: =SUM(G31:G34,G29) -> 9041.1774 | H35: =SUM(H31:H34,H29) -> 9743.289 | I35: =SUM(I31:I34,I29) -> 10515.612 | J35: =SUM(J31:J34,J29) -> 11365.167
C36: =BS!C12 -> 11791.2 | D36: =C36+D35 -> 19408.8 | E36: =D36+E35 -> 8173.6 | F36: =E36+F35 -> 20645.883 | G36: =F36+G35 -> 29687.06 | H36: =G36+H35 -> 39430.349 | I36: =H36+I35 -> 49945.961 | J36: =I36+J35 -> 61311.127

Sheet Valuation
B2: Valuation | D2: WACC | E2: 0.1
D3: G | E3: 0.02
F4: 1 | G4: 2 | H4: 3 | I4: 4 | J4: 5
C5: 16 | D5: =C5+1 -> 17 | E5: =D5+1 -> 18 | F5: =E5+1 -> 19 | G5: =F5+1 -> 20 | H5: =G5+1 -> 21 | I5: =H5+1 -> 22 | J5: =I5+1 -> 23
C6: Actual | D6: Actual | E6: Actual | F6: Forecast | G6: Forecast | H6: Forecast | I6: Forecast | J6: Forecast
B7: {=CF!B29:J29} -> UFCF | C7: 0 | D7: 3980.5256 | E7: 2517.8757 | F7: 14762.191 | G7: 11560.076 | H7: 12514.078 | I7: 13563.479 | J7: 14717.821
C9: PV of UFCF | F9: =F7/(1+$E$2)^F4 -> 13420.173 | G9: =G7/(1+$E$2)^G4 -> 9553.7822 | H9: =H7/(1+$E$2)^H4 -> 9402.0119 | I9: =I7/(1+$E$2)^I4 -> 9264.039 | J9: =J7/(1+$E$2)^J4 -> 9138.609
C10: PV of All Cash Flows | E10: =SUM(F9:J9) -> 50778.616
C11: Horizon Value | E11: =J9*(1+E3)/(E2-E3) -> 116517.26
C12: PV of HV | E12: =E11/(1+E2)^J4 -> 72348.054
C13: Enterprize Value | E13: =SUM(E10,E12) -> 123126.67
C14: Financial Liabilities | E14: =-BS!E17 -> -51120.8
C15: Cash | E15: =BS!E12 -> 8173.6
C16: Equity Values | E16: =SUM(E13:E15) -> 80179.47
