Workbook

Sheet IS
A2: CONSOLIDATED STATEMENTS OF OPERATIONS
A6: (dollars in millions, except per share amounts) | C6: 2019 | D6: 2020 | E6: 2021
A7: Net sales:
A8: Product sales | C8: 5648 | D8: 5371 | E8: 6428
A9: Service sales | C9: 7470 | D9: 7385 | E9: 7870
C10: 13118 | D10: 12756 | E10: 14298
A11: Costs and expenses:
A12: Cost of products sold | C12: 4640 | D12: 4439 | E12: 5293
A13: Cost of services sold | C13: 4652 | D13: 4538 | E13: 4812
A14: Research and development | C14: 163 | D14: 152 | E14: 159
A15: Selling, general and administrative | C15: 1810 | D15: 1924 | E15: 1948
C16: 11265 | D16: 11053 | E16: 12212
A17: Other income (expense), net | C17: -39 | D17: -64 | E17: 22
A18: Operating profit | C18: 1814 | D18: 1639 | E18: 2108
A19: Non-service pension benefit (Cost) | C19: -33 | D19: 6 | E19: 11
A20: Interest income (expense), net | C20: -14 | D20: 122 | E20: 136
A21: Net income before income taxes | C21: 1861 | D21: 1511 | E21: 1961
A22: Income tax expense | C22: 594 | D22: 455 | E22: 541
A23: Net income | C23: 1267 | D23: 1056 | E23: 1420
A24: Less: Noncontrolling interest in subsidiaries' earnings | C24: 151 | D24: 150 | E24: 174
A33: Net income attributable to Otis | C33: 1116 | D33: 906 | E33: 1246
A37: Earnings per share (Note 3):
A39: Basic | C39: 2.55 | D39: 2.09 | E39: 2.91
A40: Diluted | C40: 2.55 | D40: 2.08 | E40: 2.89
A41: Weighted average number of shares outstanding
A42: Basic shares | C42: 433.1 | D42: 433.2 | E42: 427.7
A43: Diluted shares | C43: 433.1 | D43: 434.6 | E43: 431.4

Sheet BS
A2: CONSOLIDATED BALANCE SHEETS
A5: (dollars in millions) | D5: 2020 | E5: 2021
A6: Assets
A7: Cash and cash equivalents | D7: 1782 | E7: 1565
A8: Restricted cash | D8: 17 | E8: 1910
A9: Accounts receivable (net of allowance for expected credit losses of $175 and $161) | D9: 3148 | E9: 3232
A10: Contract assets | D10: 458 | E10: 550
A11: Inventories, net | D11: 659 | E11: 622
A12: Other current assets | D12: 429 | E12: 382
A13: Total Current Assets | D13: 6493 | E13: 8261
A14: Future income tax benefits | D14: 334 | E14: 335
A15: Fixed assets, net | D15: 774 | E15: 774
A16: Operating lease right-of-use assets | D16: 542 | E16: 526
A17: Intangible assets, net | D17: 484 | E17: 419
A18: Goodwill | D18: 1773 | E18: 1667
... A20: Total Assets | D20: 10710 | E20: 12279
A21: Liabilities and (Deficit) Equity
A22: Short-term borrowings | D22: 701 | E22: 24
A23: Accounts payable | D23: 1453 | E23: 1556
A24: Accrued liabilities | D24: 1977 | E24: 1993
A25: Contract liabilities | D25: 2542 | E25: 2674
A27: Total Current Liabilities | D27: 6673 | E27: 6247
A28: Long-term debt | D28: 5262 | E28: 7249
A29: Future pension and postretirement benefit obligations | D29: 654 | E29: 558
A30: Operating lease liabilities | D30: 367 | E30: 336
A31: Future income tax obligations | D31: 321 | E31: 267
A32: Other long-term liabilities | D32: 634 | E32: 606
A33: Total Liabilities | D33: 13911 | E33: 15263
A34: Commitments and contingent liabilities (Note 22)
A35: Redeemable noncontrolling interest | D35: 194 | E35: 160
A36: Shareholders' (Deficit) Equity:
A37: Common Stock and additional paid-in-capital | D37: 59 | E37: 119
A38: Treasury Stock | D38: — | E38: -725
A40: Accumulated deficit | D40: -3106 | E40: -2256
A42: Accumulated other comprehensive income (loss) | D42: -815 | E42: -763
A43: Total Shareholders' (Deficit) Equity | D43: -3862 | E43: -3625
A44: Noncontrolling interest | D44: 467 | E44: 481
A45: Total (Deficit) Equity | D45: -3395 | E45: -3144
A46: Total Liabilities and (Deficit) Equity | D46: 10710 | E46: 12279

Sheet CF
A2: CONSOLIDATED STATEMENTS OF CASH FLOWS
A5: (dollars in millions) | C5: 2019 | D5: 2020 | E5: 2021
A6: Operating Activities:
A7: Net income | C7: 1267 | D7: 1056 | E7: 1420
A8: Adjustments to reconcile net income to net cash flows provided by operating activities, net of acquisitions:
A9: Depreciation and amortization | C9: 180 | D9: 191 | E9: 203
A10: Deferred income tax expense (benefit) | C10: -8 | D10: -51 | E10: -92
A11: Stock compensation cost | C11: 37 | D11: 63 | E11: 65
A12: Losses on fixed asset impairment or disposal of business | C12: 26 | D12: 71 | E12: 0
A15: Change in:
A16: Accounts receivable, net | C16: -191 | D16: -163 | E16: -152
A17: Contract assets and liabilities, current | C17: 97 | D17: 282 | E17: 53
A18: Inventories, net | C18: 60 | D18: -76 | E18: 14
A19: Other current assets | C19: 30 | D19: 28 | E19: 43
A20: Accounts payable | C20: 6 | D20: 20 | E20: 130
A21: Accrued liabilities | C21: -34 | D21: -14 | E21: 72
A24: Pension contributions | C24: -32 | D24: -64 | E24: -37
A25: Other operating activities, net | C25: 31 | D25: 137 | E25: 31
A26: Net cash flows provided by operating activities | C26: 1469 | D26: 1480 | E26: 1750
A27: Investing Activities:
A28: Capital expenditures | C28: -145 | D28: -183 | E28: -156
A29: Investments in businesses and intangible assets, net of cash acquired (Note 9) | C29: -47 | D29: -53 | E29: -80
A30: Proceeds from sale of (investments in) equity securities | C30: 0 | D30: -51 | E30: 40
A32: Receipts (payments) on settlements of derivative contracts | C32: -5 | D32: -69 | E32: 73
A33: Other investing activities, net | C33: -6 | D33: 3 | E33: 34
A34: Net cash flows used in investing activities | C34: -203 | D34: -353 | E34: -89
A35: Financing Activities:
A36: Net proceeds from (repayments of) borrowings (maturities of 90 days or less) | C36: 6 | D36: 647 | E36: -304
A37: Proceeds from borrowings (maturities longer than 90 days) | C37: 0 | D37: 0 | E37: 152
A38: Repayments of borrowings (maturities longer than 90 days) | C38: 0 | D38: 0 | E38: -503
A39: Proceeds from issuance of long-term debt | C39: 0 | D39: 6300 | E39: 2030
A40: Payment of debt issuance costs | C40: 0 | D40: -43 | E40: -25
A41: Repayment of long-term debt | C41: 0 | D41: -1000 | E41: 0
A43: Dividends paid on Common Stock | C43: 0 | D43: -260 | E43: -393
A44: Repurchases of Common Stock | C44: 0 | D44: 0 | E44: -725
A45: Dividends paid to noncontrolling interest | C45: -163 | D45: -149 | E45: -155
A46: Net transfers to UTC | C46: -972 | D46: -6330 | E46: 0
A47: Other financing activities, net | C47: -4 | D47: -9 | E47: -19
A48: Net cash flows provided by (used in) financing activities | C48: -1133 | D48: -844 | E48: 58
... A55: Cash and cash equivalents, end of period | C55: 1446 | D55: 1782 | E55: 1565
A56: Supplemental cash flow information:
A57: Interest paid (including related party interest of $0, $0 and $18) | C57: 18 | D57: 81 | E57: 129
A58: Income taxes paid, net of (refunds) (including related party of $0, $(15) and $255) | C58: 632 | D58: 561 | E58: 552

Sheet MODEL
B1: Otis | D1: 2019 | E1: =D1+1 -> 2020 | F1: =E1+1 -> 2021 | G1: =F1+1 -> 2022 | H1: =G1+1 -> 2023 | I1: =H1+1 -> 2024 | J1: =I1+1 -> 2025 | K1: =J1+1 -> 2026
B3: Market Size | D3: =D40/D5 -> 35300 | E3: =E40/E5 -> 31594.118 | F3: =F40/F5 -> 35711.111 | G3: =F3*(1+G4) -> 37496.667 | H3: =G3*(1+H4) -> 39371.5 | I3: =H3*(1+I4) -> 41340.075 | J3: =I3*(1+J4) -> 43407.079 | K3: =J3*(1+K4) -> 45577.433
B4: Market Growth Rate | E4: =E3/D3-1 -> -0.1049825 | F4: =F3/E3-1 -> 0.13030886 | G4: 0.05 | H4: 0.05 | I4: 0.05 | J4: 0.05 | K4: 0.05
B5: Product Market Share | D5: 0.16 | E5: 0.17 | F5: 0.18 | G5: =F5 -> 0.18 | H5: =G5 -> 0.18 | I5: 0.182 | J5: 0.184 | K5: 0.186
B7: Service units | D7: 2 | E7: 2.1 | F7: 2.15 | G7: =F7*(1+G8) -> 2.2145 | H7: =G7*(1+H8) -> 2.280935 | I7: =H7*(1+I8) -> 2.351644 | J7: =I7*(1+J8) -> 2.4268966 | K7: =J7*(1+K8) -> 2.5069842
E8: =E7/D7-1 -> 0.05 | F8: =F7/E7-1 -> 0.023809524 | G8: 0.03 | H8: 0.03 | I8: 0.031 | J8: 0.032 | K8: 0.033
B10: Revenue Units | D10: =D41/D7 -> 3735 | E10: =E41/E7 -> 3516.6667 | F10: =F41/F7 -> 3660.4651 | G10: =F10*(1+G11) -> 3806.8837 | H10: =G10*(1+H11) -> 3940.1247 | I10: =H10*(1+I11) -> 4078.029 | J10: =I10*(1+J11) -> 4220.76 | K10: =J10*(1+K11) -> 4368.4866
E11: =E10/D10-1 -> -0.058456046 | F11: =F10/E10-1 -> 0.040890554 | G11: 0.04 | H11: 0.035 | I11: =H11 -> 0.035 | J11: =I11 -> 0.035 | K11: =J11 -> 0.035
B12: COPS as % of Product sales | D12: =D44/D40 -> -0.82152975 | E12: =E44/E40 -> -0.82647552 | F12: =F44/F40 -> -0.82342875 | G12: =AVERAGE(D12:F12) -> -0.82381134 | H12: =G12 -> -0.82381134 | I12: =H12 -> -0.82381134 | J12: =I12 -> -0.82381134 | K12: =J12 -> -0.82381134
B13: COSS as % of Services sales | D13: =D45/D41 -> -0.6227577 | E13: =E45/E41 -> -0.61448883 | F13: =F45/F41 -> -0.61143583 | G13: =AVERAGE(D13:F13) -> -0.61622745 | H13: =G13 -> -0.61622745 | I13: =H13 -> -0.61622745 | J13: =I13 -> -0.61622745 | K13: =J13 -> -0.61622745
B14: S&GA R&D as % of total revenue | D14: =D48/D42 -> -0.15040403 | E14: =E48/E42 -> -0.16274694 | F14: =F48/F42 -> -0.14736327 | G14: =AVERAGE(D14:F14) -> -0.15350475 | H14: =G14 -> -0.15350475 | I14: =H14 -> -0.15350475 | J14: =I14 -> -0.15350475 | K14: =J14 -> -0.15350475
B15: tax as % EBT | D15: =D58/D56 -> -0.31918323 | E15: =E58/E56 -> -0.30112508 | F15: =F58/F56 -> -0.27587965 | G15: =AVERAGE(D15:F15) -> -0.29872932 | H15: =G15 -> -0.29872932 | I15: =H15 -> -0.29872932 | J15: =I15 -> -0.29872932 | K15: =J15 -> -0.29872932
B16: NCI as % of NI | D16: =D61/D59 -> -0.11917916 | E16: =E61/E59 -> -0.14204545 | F16: =F61/F59 -> -0.12253521 | G16: =AVERAGE(D16:F16) -> -0.12791994 | H16: =G16 -> -0.12791994 | I16: =H16 -> -0.12791994 | J16: =I16 -> -0.12791994 | K16: =J16 -> -0.12791994
B17: Interest As % of Debt | E17: =E55/E79 -> -0.0204595 | F17: =F55/F79 -> -0.018699299 | G17: =AVERAGE(D17:F17) -> -0.0195794 | H17: =G17 -> -0.0195794 | I17: =H17 -> -0.0195794 | J17: =I17 -> -0.0195794 | K17: =J17 -> -0.0195794
B19: Total Expenses | E19: =E44+E45+E48 -> -11053 | F19: =F44+F45+F48 -> -12212 | G19: =G44+G45+G48 -> -13085.404 | H19: =H44+H45+H48 -> -13843.825 | I19: =I44+I45+I48 -> -14735.01 | J19: =J44+J45+J48 -> -15690.363 | K19: =K44+K45+K48 -> -16714.999
B20: Account Receivable as % Revenue | E20: =E68/E42 -> 0.24678583 | F20: =F68/F42 -> 0.2260456 | G20: =AVERAGE(E20:F20) -> 0.23641571 | H20: =G20 -> 0.23641571 | I20: =H20 -> 0.23641571 | J20: =I20 -> 0.23641571 | K20: =J20 -> 0.23641571
B21: Accounts payable as % Cog | E21: =E76/SUM(E44:E45) -> -0.16185808 | F21: =F76/SUM(F44:F45) -> -0.15398318 | G21: =AVERAGE(E21:F21) -> -0.15792063 | H21: =G21 -> -0.15792063 | I21: =H21 -> -0.15792063 | J21: =I21 -> -0.15792063 | K21: =J21 -> -0.15792063
B22: Accrued liabilities as % Total Expenses | E22: =E77/SUM(E44:E45,E48) -> -0.17886547 | F22: =F77/SUM(F44:F45,F48) -> -0.16320013 | G22: =AVERAGE(E22:F22) -> -0.1710328 | H22: =G22 -> -0.1710328 | I22: =H22 -> -0.1710328 | J22: =I22 -> -0.1710328 | K22: =J22 -> -0.1710328
B23: Contract liabilities as % of Total Expenses | E23: =E78/SUM(E44:E45,E48) -> -0.22998281 | F23: =F78/SUM(F44:F45,F48) -> -0.21896495 | G23: =AVERAGE(E23:F23) -> -0.22447388 | H23: =G23 -> -0.22447388 | I23: =H23 -> -0.22447388 | J23: =I23 -> -0.22447388 | K23: =J23 -> -0.22447388
B24: Inventory and Other Assets as % of COG | E24: =E69/SUM(E44:E45) -> -0.17221789 | F24: =F69/SUM(F44:F45) -> -0.15378525 | G24: =AVERAGE(E24:F24) -> -0.16300157 | H24: =G24 -> -0.16300157 | I24: =H24 -> -0.16300157 | J24: =I24 -> -0.16300157 | K24: =J24 -> -0.16300157
B25: Operating lease right-of-use assets as % Opex | E25: =E71/E48 -> -0.261079 | F25: =F71/F48 -> -0.24964404 | G25: =AVERAGE(E25:F25) -> -0.25536152 | H25: =G25 -> -0.25536152 | I25: =H25 -> -0.25536152 | J25: =I25 -> -0.25536152 | K25: =J25 -> -0.25536152
B26: Other Liabilities as % Total Expenses | E26: =E81/E19 -> -0.14557134 | F26: =F81/F19 -> -0.11717982 | G26: =AVERAGE(E26:F26) -> -0.13137558 | H26: =G26 -> -0.13137558 | I26: =H26 -> -0.13137558 | J26: =I26 -> -0.13137558 | K26: =J26 -> -0.13137558
B28: Depriciation as % total revenue | D28: =D94/D42 -> 0.013721604 | E28: =E94/E42 -> 0.014973346 | F28: =F94/F42 -> 0.01419779 | G28: =AVERAGE(D28:F28) -> 0.01429758 | H28: =G28 -> 0.01429758 | I28: =H28 -> 0.01429758 | J28: =I28 -> 0.01429758 | K28: =J28 -> 0.01429758
B29: Capex as % of total revenue | D29: =D100/D42 -> -0.011053514 | E29: =E100/E42 -> -0.01434619 | F29: =F100/F42 -> -0.010910617 | G29: =AVERAGE(D29:F29) -> -0.01210344 | H29: =G29 -> -0.01210344 | I29: =H29 -> -0.01210344 | J29: =I29 -> -0.01210344 | K29: =J29 -> -0.01210344
B30: Other Operating Activities As % of Rev | D30: =D97/D42 -> 0.0041164812 | E30: =E97/E42 -> 0.012229539 | F30: =F97/F42 -> -0.0023080151 | G30: =AVERAGE(D30:F30) -> 0.004679335 | H30: =G30 -> 0.004679335 | I30: =H30 -> 0.004679335 | J30: =I30 -> 0.004679335 | K30: =J30 -> 0.004679335
B31: Debt as Flat | E31: =E79 -> 5963 | F31: =F79 -> 7273 | G31: =F31 -> 7273 | H31: =G31 -> 7273 | I31: =H31 -> 7273 | J31: =I31 -> 7273 | K31: =J31 -> 7273
B32: Dividends on CS As % of NI | D32: =D105/D59 -> 0 | E32: =E105/E59 -> -0.24621212 | F32: =F105/F59 -> -0.27676056 | G32: =AVERAGE(D32:F32) -> -0.17432423 | H32: =AVERAGE(E32:G32) -> -0.2324323 | I32: =AVERAGE(F32:H32) -> -0.22783903 | J32: =AVERAGE(G32:I32) -> -0.21153185 | K32: =AVERAGE(H32:J32) -> -0.2239344
B33: No Repurchases of Common Stock | D33: 0 | E33: 0 | F33: 0 | G33: 0 | H33: 0 | I33: 0 | J33: 0 | K33: 0
B34: Dividends NCI as % of NCI Income | D34: =D107/D61 -> 1.0794702 | E34: =E107/E61 -> 0.99333333 | F34: =F107/F61 -> 0.8908046 | G34: =AVERAGE(D34:F34) -> 0.98786938 | H34: =G34 -> 0.98786938 | I34: =H34 -> 0.98786938 | J34: =I34 -> 0.98786938 | K34: =J34 -> 0.98786938
B35: Forex as % of Revenue | D35: =D110/D42 -> -0.0015246227 | E35: =E110/E42 -> 0.0046252744 | F35: =F110/F42 -> -0.0030074136 | G35: =AVERAGE(D35:F35) -> 3.1079367e-05 | H35: =G35 -> 3.1079367e-05 | I35: =H35 -> 3.1079367e-05 | J35: =I35 -> 3.1079367e-05 | K35: =J35 -> 3.1079367e-05
B36: Other Financing Activities As % of 0 | G36: 0 | H36: 0 | I36: 0 | J36: 0 | K36: 0
B38: Income Statement
B40: =IS!A8 -> Product sales | D40: =IS!C8 -> 5648 | E40: =IS!D8 -> 5371 | F40: =IS!E8 -> 6428 | G40: =G3*G5 -> 6749.4 | H40: =H3*H5 -> 7086.87 | I40: =I3*I5 -> 7523.8937 | J40: =J3*J5 -> 7986.9025 | K40: =K3*K5 -> 8477.4025
B41: =IS!A9 -> Service sales | D41: =IS!C9 -> 7470 | E41: =IS!D9 -> 7385 | F41: =IS!E9 -> 7870 | G41: =G10*G7 -> 8430.344 | H41: =H10*H7 -> 8987.1682 | I41: =I10*I7 -> 9590.0724 | J41: =J10*J7 -> 10243.348 | K41: =K10*K7 -> 10951.727
B42: Total Revenue | D42: =SUM(D40:D41) -> 13118 | E42: =SUM(E40:E41) -> 12756 | F42: =SUM(F40:F41) -> 14298 | G42: =SUM(G40:G41) -> 15179.744 | H42: =SUM(H40:H41) -> 16074.038 | I42: =SUM(I40:I41) -> 17113.966 | J42: =SUM(J40:J41) -> 18230.251 | K42: =SUM(K40:K41) -> 19429.129
B44: =IS!A12 -> Cost of products sold | D44: =-IS!C12 -> -4640 | E44: =-IS!D12 -> -4439 | F44: =-IS!E12 -> -5293 | G44: =G12*G40 -> -5560.2322 | H44: =H12*H40 -> -5838.2438 | I44: =I12*I40 -> -6198.2689 | J44: =J12*J40 -> -6579.7008 | K44: =K12*K40 -> -6983.7803
B45: =IS!A13 -> Cost of services sold | D45: =-IS!C13 -> -4652 | E45: =-IS!D13 -> -4538 | F45: =-IS!E13 -> -4812 | G45: =G13*G41 -> -5195.0094 | H45: =H13*H41 -> -5538.1398 | I45: =I13*I41 -> -5909.6659 | J45: =J13*J41 -> -6312.2323 | K45: =K13*K41 -> -6748.7548
B46: Gross Profit | D46: =SUM(D42:D45) -> 3826 | E46: =SUM(E42:E45) -> 3779 | F46: =SUM(F42:F45) -> 4193 | G46: =SUM(G42:G45) -> 4424.5024 | H46: =SUM(H42:H45) -> 4697.6546 | I46: =SUM(I42:I45) -> 5006.0313 | J46: =SUM(J42:J45) -> 5338.3175 | K46: =SUM(K42:K45) -> 5696.5943
B48: S&GA R&D | D48: =-SUM(IS!C15,IS!C14) -> -1973 | E48: =-(IS!D14+IS!D15) -> -2076 | F48: =-(IS!E14+IS!E15) -> -2107 | G48: =G14*G42 -> -2330.1627 | H48: =H14*H42 -> -2467.4411 | I48: =I14*I42 -> -2627.075 | J48: =J14*J42 -> -2798.43 | K48: =K14*K42 -> -2982.4635
B49: Operating Profit | D49: =SUM(D46:D48) -> 1853 | E49: =SUM(E46:E48) -> 1703 | F49: =SUM(F46:F48) -> 2086 | G49: =SUM(G46:G48) -> 2094.3396 | H49: =SUM(H46:H48) -> 2230.2135 | I49: =SUM(I46:I48) -> 2378.9563 | J49: =SUM(J46:J48) -> 2539.8875 | K49: =SUM(K46:K48) -> 2714.1308
B51: =IS!A17 -> Other income (expense), net | D51: =IS!C17 -> -39 | E51: =IS!D17 -> -64 | F51: =IS!E17 -> 22 | G51: =F51 -> 22 | H51: =G51 -> 22 | I51: =H51 -> 22 | J51: =I51 -> 22 | K51: =J51 -> 22
B52: =IS!A19 -> Non-service pension benefit (Cost) | D52: =-IS!C19 -> 33 | E52: =-IS!D19 -> -6 | F52: =-IS!E19 -> -11 | G52: =F52 -> -11 | H52: =G52 -> -11 | I52: =H52 -> -11 | J52: =I52 -> -11 | K52: =J52 -> -11
B53: EBIT | D53: =SUM(D49:D52) -> 1847 | E53: =SUM(E49:E52) -> 1633 | F53: =SUM(F49:F52) -> 2097 | G53: =SUM(G49:G52) -> 2105.3396 | H53: =SUM(H49:H52) -> 2241.2135 | I53: =SUM(I49:I52) -> 2389.9563 | J53: =SUM(J49:J52) -> 2550.8875 | K53: =SUM(K49:K52) -> 2725.1308
B55: =IS!A20 -> Interest income (expense), net | D55: =-IS!C20 -> 14 | E55: =-IS!D20 -> -122 | F55: =-IS!E20 -> -136 | G55: =G79*G17 -> -142.40097 | H55: =H79*H17 -> -142.40097 | I55: =I79*I17 -> -142.40097 | J55: =J79*J17 -> -142.40097 | K55: =K79*K17 -> -142.40097
B56: EBT | D56: =SUM(D53:D55) -> 1861 | E56: =SUM(E53:E55) -> 1511 | F56: =SUM(F53:F55) -> 1961 | G56: =SUM(G53:G55) -> 1962.9386 | H56: =SUM(H53:H55) -> 2098.8125 | I56: =SUM(I53:I55) -> 2247.5553 | J56: =SUM(J53:J55) -> 2408.4865 | K56: =SUM(K53:K55) -> 2582.7298
B58: =IS!A22 -> Income tax expense | D58: =-IS!C22 -> -594 | E58: =-IS!D22 -> -455 | F58: =-IS!E22 -> -541 | G58: =G56*G15 -> -586.38733 | H58: =H56*H15 -> -626.97683 | I58: =I56*I15 -> -671.41068 | J58: =J56*J15 -> -719.48555 | K58: =K56*K15 -> -771.53713
B59: Net Income | D59: =SUM(D56:D58) -> 1267 | E59: =SUM(E56:E58) -> 1056 | F59: =SUM(F56:F58) -> 1420 | G59: =SUM(G56:G58) -> 1376.5513 | H59: =SUM(H56:H58) -> 1471.8356 | I59: =SUM(I56:I58) -> 1576.1446 | J59: =SUM(J56:J58) -> 1689.001 | K59: =SUM(K56:K58) -> 1811.1927
B61: NCI | D61: =-IS!C24 -> -151 | E61: =-IS!D24 -> -150 | F61: =-IS!E24 -> -174 | G61: =G59*G16 -> -176.08837 | H61: =H59*H16 -> -188.27713 | I61: =I59*I16 -> -201.62033 | J61: =J59*J16 -> -216.05691 | K61: =K59*K16 -> -231.68766
B62: =IS!A33 -> Net income attributable to Otis | D62: =SUM(D59:D61) -> 1116 | E62: =SUM(E59:E61) -> 906 | F62: =SUM(F59:F61) -> 1246 | G62: =SUM(G59:G61) -> 1200.4629 | H62: =SUM(H59:H61) -> 1283.5585 | I62: =SUM(I59:I61) -> 1374.5243 | J62: =SUM(J59:J61) -> 1472.9441 | K62: =SUM(K59:K61) -> 1579.505
B64: Balance Sheet
B66: Assets
B67: Cash | E67: =SUM(BS!D7:D8) -> 1799 | F67: =SUM(BS!E7:E8) -> 3475 | G67: =F67+G111 -> 4850.5328 | H67: =G67+H111 -> 6015.2742 | I67: =H67+I111 -> 7296.2786 | J67: =I67+J111 -> 8700.9059 | K67: =J67+K111 -> 10188.94
A68: B | B68: Account Receivable | E68: =BS!D9 -> 3148 | F68: =BS!E9 -> 3232 | G68: =G20*G42 -> 3588.73 | H68: =H20*H42 -> 3800.1552 | I68: =I20*I42 -> 4046.0105 | J68: =J20*J42 -> 4309.9177 | K68: =K20*K42 -> 4593.3515
A69: B | B69: Inventory and Other Assets | E69: =SUM(BS!D10:D12) -> 1546 | F69: =SUM(BS!E10:E12) -> 1554 | G69: =G24*(SUM(G44:G45)) -> 1753.1213 | H69: =H24*(SUM(H44:H45)) -> 1854.3684 | I69: =I24*(SUM(I44:I45)) -> 1973.6124 | J69: =J24*(SUM(J44:J45)) -> 2101.4054 | K69: =K24*(SUM(K44:K45)) -> 2238.4248
A70: A | B70: PP&E and Int Assets | E70: =SUM(BS!D15,BS!D17,BS!D18) -> 3031 | F70: =SUM(BS!E15,BS!E17,BS!E18) -> 2860 | G70: =F70-G100-G94 -> 2826.6935 | H70: =G70-H100-H94 -> 2791.4248 | I70: =H70-I100-I94 -> 2753.8744 | J70: =I70-J100-J94 -> 2713.8747 | K70: =J70-K100-K94 -> 2671.2445
A71: B | B71: =BS!A16 -> Operating lease right-of-use assets | E71: =BS!D16 -> 542 | F71: =BS!E16 -> 526 | G71: =G25*G48 -> 595.0339 | H71: =H25*H48 -> 630.08952 | I71: =I25*I48 -> 670.85387 | J71: =J25*J48 -> 714.61133 | K71: =K25*K48 -> 761.60643
A72: A | B72: Other Assets | E72: =SUM(BS!D14,BS!D19) -> 644 | F72: =SUM(BS!E14,BS!E19) -> 632 | G72: =F72-G97-G101 -> 635.96889 | H72: =G72-H97-H101 -> 635.75308 | I72: =H72-I97-I101 -> 630.6711 | J72: =I72-J97-J101 -> 620.36565 | K72: =J72-K97-K101 -> 604.45024
B73: Total Assets | E73: =SUM(E67:E72) -> 10710 | F73: =SUM(F67:F72) -> 12279 | G73: =SUM(G67:G72) -> 14250.08 | H73: =SUM(H67:H72) -> 15727.065 | I73: =SUM(I67:I72) -> 17371.301 | J73: =SUM(J67:J72) -> 19161.081 | K73: =SUM(K67:K72) -> 21058.017
B75: Liabilites
A76: B | B76: =BS!A23 -> Accounts payable | E76: =BS!D23 -> 1453 | F76: =BS!E23 -> 1556 | G76: =G21*SUM(G44:G45) -> 1698.4745 | H76: =H21*SUM(H44:H45) -> 1796.5657 | I76: =I21*SUM(I44:I45) -> 1912.0927 | J76: =J21*SUM(J44:J45) -> 2035.9022 | K76: =K21*SUM(K44:K45) -> 2168.6506
A77: B | B77: =BS!A24 -> Accrued liabilities | E77: =BS!D24 -> 1977 | F77: =BS!E24 -> 1993 | G77: =G22*G19 -> 2238.0333 | H77: =H22*H19 -> 2367.7481 | I77: =I22*I19 -> 2520.17 | J77: =J22*J19 -> 2683.5667 | K77: =K22*K19 -> 2858.813
A78: B | B78: =BS!A25 -> Contract liabilities | E78: =BS!D25 -> 2542 | F78: =BS!E25 -> 2674 | G78: =G23*G19 -> 2937.3315 | H78: =H23*H19 -> 3107.5771 | I78: =I23*I19 -> 3307.6248 | J78: =J23*J19 -> 3522.0767 | K78: =K23*K19 -> 3752.0806
B79: Debt | E79: =SUM(BS!D22,BS!D28) -> 5963 | F79: =SUM(BS!E22,BS!E28) -> 7273 | G79: {=G31:K31} -> 7273 | H79: 7273 | I79: 7273 | J79: 7273 | K79: 7273
A80: B | B80: =BS!A30 -> Operating lease liabilities | E80: =BS!D30 -> 367 | F80: =BS!E30 -> 336 | G80: =F80+G71-F71 -> 405.0339 | H80: =G80+H71-G71 -> 440.08952 | I80: =H80+I71-H71 -> 480.85387 | J80: =I80+J71-I71 -> 524.61133 | K80: =J80+K71-J71 -> 571.60643
A81: B | B81: Other Liabilities | E81: =SUM(BS!D29,BS!D31,BS!D32) -> 1609 | F81: =SUM(BS!E29,BS!E31,BS!E32) -> 1431 | G81: =G26*G19 -> 1719.1026 | H81: =H26*H19 -> 1818.7405 | I81: =I26*I19 -> 1935.8205 | J81: =J26*J19 -> 2061.3306 | K81: =K26*K19 -> 2195.9426
B82: Total Liabilites | E82: =SUM(E76:E81) -> 13911 | F82: =SUM(F76:F81) -> 15263 | G82: =SUM(G76:G81) -> 16270.976 | H82: =SUM(H76:H81) -> 16803.721 | I82: =SUM(I76:I81) -> 17429.562 | J82: =SUM(J76:J81) -> 18100.488 | K82: =SUM(K76:K81) -> 18820.093
A84: A | B84: NCI Equity | E84: =SUM(BS!D35,BS!D44) -> 661 | F84: =SUM(BS!E35,BS!E44) -> 641 | G84: =F84+G95+G107 -> 643.13606 | H84: =G84+H95+H107 -> 645.41998 | I84: =H84+I95+I107 -> 647.86576 | J84: =I84+J95+J107 -> 650.48667 | K84: =J84+K95+K107 -> 653.29718
A85: A | B85: Shareholders Equity (Debt) | E85: =BS!D43 -> -3862 | F85: =BS!E43 -> -3625 | G85: =F85+G93+G105+G106+G108+G110 -> -2664.0315 | H85: =G85+H93+H105+H106+H108+H110 -> -1722.0756 | I85: =H85+I93+I105+I106+I108+I110 -> -706.12666 | J85: =I85+J93+J105+J106+J108+J110 -> 410.10648 | K85: =J85+K93+K105+K106+K108+K110 -> 1584.627
B86: Total Equity | E86: =SUM(E84:E85) -> -3201 | F86: =SUM(F84:F85) -> -2984 | G86: =SUM(G84:G85) -> -2020.8955 | H86: =SUM(H84:H85) -> -1076.6556 | I86: =SUM(I84:I85) -> -58.260902 | J86: =SUM(J84:J85) -> 1060.5931 | K86: =SUM(K84:K85) -> 2237.9242
B87: Total Liabilities & Equity | E87: =SUM(E82,E86) -> 10710 | F87: =SUM(F82,F86) -> 12279 | G87: =SUM(G82,G86) -> 14250.08 | H87: =SUM(H82,H86) -> 15727.065 | I87: =SUM(I82,I86) -> 17371.301 | J87: =SUM(J82,J86) -> 19161.081 | K87: =SUM(K82,K86) -> 21058.017
B89: Check | E89: =E87-E73 -> 0 | F89: =F87-F73 -> 0 | G89: =G87-G73 -> 0 | H89: =H87-H73 -> 0 | I89: =I87-I73 -> 0 | J89: =J87-J73 -> 0 | K89: =K87-K73 -> 0
B91: Cash Flow
A93: B | B93: Net Income | D93: =D62 -> 1116 | E93: =E62 -> 906 | F93: =F62 -> 1246 | G93: =G62 -> 1200.4629 | H93: =H62 -> 1283.5585 | I93: =I62 -> 1374.5243 | J93: =J62 -> 1472.9441 | K93: =K62 -> 1579.505
A94: B | B94: (+) Dep | D94: =CF!C9 -> 180 | E94: =CF!D9 -> 191 | F94: =CF!E9 -> 203 | G94: =G28*G42 -> 217.0336 | H94: =H28*H42 -> 229.81985 | I94: =I28*I42 -> 244.6883 | J94: =J28*J42 -> 260.64846 | K94: =K28*K42 -> 277.78953
A95: B | B95: (+) NCI | D95: =-D61 -> 151 | E95: =-E61 -> 150 | F95: =-F61 -> 174 | G95: =-G61 -> 176.08837 | H95: =-H61 -> 188.27713 | I95: =-I61 -> 201.62033 | J95: =-J61 -> 216.05691 | K95: =-K61 -> 231.68766
A96: A | B96: (+/-) Changes in Working Capital | D96: =SUM(CF!C16:C21) -> -32 | E96: =SUM(CF!D16:D21) -> 77 | F96: =SUM(CF!E16:E21) -> 160 | G96: =(G76-F76)+(G77-F77)+(G78-F78)+(G80-F80)+(G81-F81)-(+G68-F68)-(G69-F69)-(G71-F71) -> 383.09066 | H96: =(H76-G76)+(H77-G77)+(H78-G78)+(H80-G80)+(H81-G81)-(+H68-G68)-(H69-G69)-(H71-G71) -> 185.01706 | I96: =(I76-H76)+(I77-H77)+(I78-H78)+(I80-H80)+(I81-H81)-(+I68-H68)-(I69-H69)-(I71-H71) -> 219.97732 | J96: =(J76-I76)+(J77-I77)+(J78-I78)+(J80-I80)+(J81-I81)-(+J68-I68)-(J69-I69)-(J71-I71) -> 235.46807 | K96: =(K76-J76)+(K77-J77)+(K78-J78)+(K80-J80)+(K81-J81)-(+K68-J68)-(K69-J69)-(K71-J71) -> 252.15742
A97: B | B97: (+/-) Other Operating Activites | D97: =SUM(CF!C10:C12,CF!C24:C25) -> 54 | E97: =SUM(CF!D10:D12,CF!D24:D25) -> 156 | F97: =SUM(CF!E10:E12,CF!E24:E25) -> -33 | G97: =G42*G30 -> 71.031108 | H97: =H42*H30 -> 75.21581 | I97: =I42*I30 -> 80.081981 | J97: =J42*J30 -> 85.30545 | K97: =K42*K30 -> 90.915406
B98: Cash Flow From Operating Activites | D98: =SUM(D93:D97) -> 1469 | E98: =SUM(E93:E97) -> 1480 | F98: =SUM(F93:F97) -> 1750 | G98: =SUM(G93:G97) -> 2047.7067 | H98: =SUM(H93:H97) -> 1961.8884 | I98: =SUM(I93:I97) -> 2120.8922 | J98: =SUM(J93:J97) -> 2270.423 | K98: =SUM(K93:K97) -> 2432.055
A100: B | B100: Capex | D100: =CF!C28 -> -145 | E100: =CF!D28 -> -183 | F100: =CF!E28 -> -156 | G100: =G29*G42 -> -183.72713 | H100: =H29*H42 -> -194.55116 | I100: =I29*I42 -> -207.13787 | J100: =J29*J42 -> -220.64875 | K100: =K29*K42 -> -235.15931
A101: B | B101: Other Investing Activites | D101: =SUM(CF!C29:C33) -> -58 | E101: =SUM(CF!D29:D33) -> -170 | F101: =SUM(CF!E29:E33) -> 67 | G101: -75 | H101: =G101 -> -75 | I101: =H101 -> -75 | J101: =I101 -> -75 | K101: =J101 -> -75
B102: Cash Flow From Investing Activites | D102: =SUM(D100:D101) -> -203 | E102: =SUM(E100:E101) -> -353 | F102: =SUM(F100:F101) -> -89 | G102: =SUM(G100:G101) -> -258.72713 | H102: =SUM(H100:H101) -> -269.55116 | I102: =SUM(I100:I101) -> -282.13787 | J102: =SUM(J100:J101) -> -295.64875 | K102: =SUM(K100:K101) -> -310.15931
B104: Debt | D104: =SUM(CF!C36:C39,CF!C41) -> 6 | E104: =SUM(CF!D36:D39,CF!D41) -> 5947 | F104: =SUM(CF!E36:E39,CF!E41) -> 1375 | G104: =G79-F79 -> 0 | H104: =H79-G79 -> 0 | I104: =I79-H79 -> 0 | J104: =J79-I79 -> 0 | K104: =K79-J79 -> 0
A105: B | B105: =CF!A43 -> Dividends paid on Common Stock | D105: =CF!C43 -> 0 | E105: =CF!D43 -> -260 | F105: =CF!E43 -> -393 | G105: =G59*G32 -> -239.96625 | H105: =H59*H32 -> -342.10215 | I105: =I59*I32 -> -359.10727 | J105: =J59*J32 -> -357.27751 | K105: =K59*K32 -> -405.58834
A106: B | B106: =CF!A44 -> Repurchases of Common Stock | D106: =CF!C44 -> 0 | E106: =CF!D44 -> 0 | F106: =CF!E44 -> -725 | G106: =G33 -> 0 | H106: =H33 -> 0 | I106: =I33 -> 0 | J106: =J33 -> 0 | K106: =K33 -> 0
A107: B | B107: =CF!A45 -> Dividends paid to noncontrolling interest | D107: =CF!C45 -> -163 | E107: =CF!D45 -> -149 | F107: =CF!E45 -> -155 | G107: =G61*G34 -> -173.9523 | H107: =H61*H34 -> -185.99321 | I107: =I61*I34 -> -199.17455 | J107: =J61*J34 -> -213.436 | K107: =K61*K34 -> -228.87715
A108: B | B108: Other Financing activites | D108: =SUM(CF!C40,CF!C46:C47) -> -976 | E108: =SUM(CF!D40,CF!D46:D47) -> -6382 | F108: =SUM(CF!E40,CF!E46:E47) -> -44 | G108: =G36 -> 0 | H108: =H36 -> 0 | I108: =I36 -> 0 | J108: =J36 -> 0 | K108: =K36 -> 0
B109: Cash Flow From Financing Activites | D109: =SUM(D104:D108) -> -1133 | E109: =SUM(E104:E108) -> -844 | F109: =SUM(F104:F108) -> 58 | G109: =SUM(G104:G108) -> -413.91855 | H109: =SUM(H104:H108) -> -528.09536 | I109: =SUM(I104:I108) -> -558.28182 | J109: =SUM(J104:J108) -> -570.71351 | K109: =SUM(K104:K108) -> -634.46549
A110: B | B110: Forex effect | D110: =CF!C50 -> -20 | E110: =CF!D50 -> 59 | F110: =CF!E50 -> -43 | G110: =G42*G35 -> 0.47177683 | H110: =H42*H35 -> 0.49957093 | I110: =I42*I35 -> 0.53189123 | J110: =J42*J35 -> 0.56658465 | K110: =K42*K35 -> 0.60384504
B111: Net Cash Flow | D111: =SUM(D109:D110,D102,D98) -> 113 | E111: =SUM(E109:E110,E102,E98) -> 342 | F111: =SUM(F109:F110,F102,F98) -> 1676 | G111: =SUM(G109:G110,G102,G98) -> 1375.5328 | H111: =SUM(H109:H110,H102,H98) -> 1164.7414 | I111: =SUM(I109:I110,I102,I98) -> 1281.0044 | J111: =SUM(J109:J110,J102,J98) -> 1404.6273 | K111: =SUM(K109:K110,K102,K98) -> 1488.0341
